flask_ua_enricher/__init__.py
flask_ua_enricher/flask_sec_ch_ua.py
Flask_UA_Enricher-0.0.1.dist-info/LICENSE
Flask_UA_Enricher-0.0.1.dist-info/METADATA
Flask_UA_Enricher-0.0.1.dist-info/WHEEL
Flask_UA_Enricher-0.0.1.dist-info/top_level.txt
Flask_UA_Enricher-0.0.1.dist-info/RECORD
