Metadata-Version: 2.1
Name: Flask-UA-Enricher
Version: 0.0.1
Summary: Decorates flask views and enrich User-Agent header in case of reduced UA string
Home-page: https://github.com/agentzex/flask-Sec-CH-UA
Author: agentzex
Author-email: cypy919@gmail.com
License: MIT
Keywords: flask,flask-ua,flask-ua-enricher,flask-Sec-CH-UA,flask-useragent-enrich,flask-useragent-enricher,flask-sec-ua,useragent-enricher
Platform: any
Classifier: Framework :: Flask
Classifier: Intended Audience :: Developers
Classifier: License :: OSI Approved :: MIT License
Classifier: Operating System :: OS Independent
Classifier: Programming Language :: Python
Classifier: Programming Language :: Python :: 3
Classifier: Topic :: Software Development :: Libraries :: Python Modules
Requires-Python: >=3.6
Requires-Dist: flask (>=2.0.0)
